README.md
setup.py
lecert/__init__.py
lecert.egg-info/PKG-INFO
lecert.egg-info/SOURCES.txt
lecert.egg-info/dependency_links.txt
lecert.egg-info/requires.txt
lecert.egg-info/top_level.txt