Metadata-Version: 2.1
Name: lecert
Version: 1.1
Summary: Python module for obtaining SSL certificates from Let's Encrypt for self-service projects
Home-page: https://github.com/EightShift/lecert
Author: EightShift
Author-email: the8shift@gmail.com
Classifier: Programming Language :: Python :: 3
Classifier: License :: OSI Approved :: MIT License
Classifier: Operating System :: OS Independent
